aixtract/__init__.py
aixtract/cli.py
aixtract-1.0.0.dist-info/METADATA
aixtract-1.0.0.dist-info/WHEEL
aixtract-1.0.0.dist-info/entry_points.txt
aixtract-1.0.0.dist-info/RECORD
