Metadata-Version: 2.3
Name: aixtract
Version: 1.0.0
Summary: Utility to prepare files for AI analysis
License: MIT
Author: The Zealot
Requires-Python: >=3.13,<4.0
Classifier: License :: OSI Approved :: MIT License
Classifier: Programming Language :: Python :: 3
Classifier: Programming Language :: Python :: 3.13
